LICENSE
MANIFEST.in
README.md
setup.py
testflows.stash.egg-info/PKG-INFO
testflows.stash.egg-info/SOURCES.txt
testflows.stash.egg-info/dependency_links.txt
testflows.stash.egg-info/not-zip-safe
testflows.stash.egg-info/requires.txt
testflows.stash.egg-info/top_level.txt
testflows/stash/__init__.py
testflows/stash/stash.py
testflows/stash/contrib/jsonpickle/__init__.py
testflows/stash/contrib/jsonpickle/backend.py
testflows/stash/contrib/jsonpickle/compat.py
testflows/stash/contrib/jsonpickle/handlers.py
testflows/stash/contrib/jsonpickle/pickler.py
testflows/stash/contrib/jsonpickle/tags.py
testflows/stash/contrib/jsonpickle/unpickler.py
testflows/stash/contrib/jsonpickle/util.py
testflows/stash/contrib/jsonpickle/version.py
tests/tests.py